CHANGELOG.md
LICENSE
README.md
deliver.sh
setup.cfg
setup.py
tu.sh
src/langutil/JFile.py
src/langutil/StrOoo.py
src/langutil/__init__.py
src/pypos3d/__init__.py
src/pypos3d.egg-info/PKG-INFO
src/pypos3d.egg-info/SOURCES.txt
src/pypos3d.egg-info/dependency_links.txt
src/pypos3d.egg-info/requires.txt
src/pypos3d.egg-info/top_level.txt
src/pypos3d/dztk/Loader.py
src/pypos3d/dztk/__init__.py
src/pypos3d/pftk/ChannelImportAnalysis.py
src/pypos3d/pftk/Figure.py
src/pypos3d/pftk/GeomCustom.py
src/pypos3d/pftk/PoserBasic.py
src/pypos3d/pftk/PoserFile.py
src/pypos3d/pftk/PoserMeshed.py
src/pypos3d/pftk/SimpleAttribut.py
src/pypos3d/pftk/StructuredAttribut.py
src/pypos3d/pftk/__init__.py
src/pypos3d/propslim/MxBasic.py
src/pypos3d/propslim/MxStdModel.py
src/pypos3d/propslim/PropSlim.py
src/pypos3d/propslim/__init__.py
src/pypos3d/wftk/GeomGroup.py
src/pypos3d/wftk/PaveList2D.py
src/pypos3d/wftk/PoserFileParser.py
src/pypos3d/wftk/Repere.py
src/pypos3d/wftk/UVRender.py
src/pypos3d/wftk/WFBasic.py
src/pypos3d/wftk/WaveGeom.py
src/pypos3d/wftk/__init__.py